{"asset": {                "version": "0.0",                "gltfUpAxis": "Y"            },            "geometricError":100.000000,"root": {                "transform": [-0.570484,0.821309,0.000000,0.000000,-0.434243,-0.301627,0.848796,0.000000,0.695809,0.483312,0.531281,0.000000,4442165.046622,3085544.808915,3369082.427796,1],                "boundingVolume": {                    "region": [0.607043,0.560083,0.607147,0.560140,0.000000,40.000000]},"geometricError": 100.000000,                        "refine": "REPLACE",                        "content": {                            "uri": "./tile/3/3/6.b3dm"}}}