{"asset": {                "version": "0.0",                "gltfUpAxis": "Y"            },            "geometricError":100.000000,"root": {                "transform": [-0.570647,0.821195,0.000000,0.000000,-0.434183,-0.301713,0.848796,0.000000,0.695713,0.483450,0.531281,0.000000,4441551.141003,3086427.971821,3369082.856164,1],                "boundingVolume": {                    "region": [0.607243,0.560084,0.607345,0.560140,0.000000,132.000000]},"geometricError": 100.000000,                        "refine": "REPLACE",                        "content": {                            "uri": "./tile/3/5/6.b3dm"}}}